MANIFEST.in
README.rst
development.txt
requirements.txt
setup.cfg
setup.py
todo.rst
chemist/__init__.py
chemist/exceptions.py
chemist/managers.py
chemist/models.py
chemist/orm.py
chemist/version.py
chemist.egg-info/PKG-INFO
chemist.egg-info/SOURCES.txt
chemist.egg-info/dependency_links.txt
chemist.egg-info/entry_points.txt
chemist.egg-info/not-zip-safe
chemist.egg-info/requires.txt
chemist.egg-info/top_level.txt
chemist/serializers/__init__.py
chemist/serializers/json.py